README.md
setup.cfg
setup.py
morphounit/__init__.py
morphounit/utils.py
morphounit.egg-info/PKG-INFO
morphounit.egg-info/SOURCES.txt
morphounit.egg-info/dependency_links.txt
morphounit.egg-info/requires.txt
morphounit.egg-info/top_level.txt
morphounit/capabilities/__init__.py
morphounit/capabilities/cap_HandlesNeuroM.py
morphounit/capabilities/cap_ProvidesDensityInfo.py
morphounit/capabilities/cap_ProvidesLayerInfo.py
morphounit/capabilities/cap_ProvidesMorphFeatureInfo.py
morphounit/plots/__init__.py
morphounit/plots/plot_error_plot.py
morphounit/plots/plot_feats_pop_morp_stats.py
morphounit/plots/plot_json_morph_stats.py
morphounit/plots/plot_score_bars_morp_stats.py
morphounit/plots/plot_txt_table.py
morphounit/plots/plot_txt_table_morph_stats.py
morphounit/scores/__init__.py
morphounit/scores/score_CombineZScores.py
morphounit/scores/score_RangeCheck.py
morphounit/scores/score_RangeScore.py
morphounit/tests/__init__.py
morphounit/tests/morph_cells/__init__.py
morphounit/tests/morph_cells/test_NeuroM_MorphCheck.py
morphounit/tests/morph_cells/test_NeuroM_MorphStats.py
morphounit/tests/morph_cells/test_NeuroM_MorphStats_pop.py
morphounit/tests/morph_cells/test_NeuroM_SomaDiamTest_Range.py
morphounit/tests/morph_circuits/__init__.py
morphounit/tests/morph_circuits/test_CellDensityTest.py
morphounit/tests/morph_circuits/test_LayerHeightTest.py