Metadata-Version: 1.0
Name: morphounit
Version: 1.0.4
Summary: A SciUnit library for data-driven testing of neuronal morphologies.
Home-page: https://github.com/appukuttan-shailesh/morphounit
Author: Shailesh Appukuttan, Pedro Garcia-Rodriguez
Author-email: shailesh.appukuttan@cnrs.fr, pedro.garcia@cnrs.fr
License: MIT
Keywords: morphology,structure,circuit,testing,validation framework
Platform: UNKNOWN
